torchde/__about__.py
torchde/__init__.py
torchde/main.py
torchde/utils.py
torchde/data/__init__.py
torchde/data/module.py
torchde/data/multivariate_normal.py
torchde/data/utils.py
torchde/models/__init__.py
torchde/models/backbone.py
torchde/models/cnn.py
torchde/models/made.py
torchde/models/mlp.py
torchde/models/normflow.py
torchde/models/utils.py
torchde/models/layers/__init__.py
torchde/models/layers/activations.py
torchde/models/layers/density_estimation.py
torchde/models/layers/linear_block.py
torchde/models/layers/ordered_block.py
torchde/models/layers/ordered_linear.py
torchde/models/layers/ordered_residual.py
torchde/models/layers/ordering_mixin.py
torchde/training/__init__.py
torchde/training/attack.py
torchde/training/callbacks.py
torchde/training/criterion.py
torchde/training/module.py
torchde/training/terms.py
torchde/training/utils.py
torchde/training/encoding/__init__.py
torchde/training/encoding/criterion.py
torchde/training/encoding/module.py
torchde/training/encoding/terms.py
torchde/training/made/__init__.py
torchde/training/made/callbacks.py
torchde/training/made/criterion.py
torchde/training/made/terms.py
torchde/training/sgld/__init__.py
torchde/training/sgld/callbacks.py
torchde/training/sgld/criterion.py
torchde/training/sgld/module.py
torchde/training/sgld/sampler.py
torchde/training/sgld/terms.py
torchde-0.0.12.dist-info/LICENSE
torchde-0.0.12.dist-info/METADATA
torchde-0.0.12.dist-info/WHEEL
torchde-0.0.12.dist-info/entry_points.txt
torchde-0.0.12.dist-info/top_level.txt
torchde-0.0.12.dist-info/RECORD
